README
setup.py
api/__init__.py
api/browserstack.py
api/rest.py
browserstack.egg-info/PKG-INFO
browserstack.egg-info/SOURCES.txt
browserstack.egg-info/dependency_links.txt
browserstack.egg-info/entry_points.txt
browserstack.egg-info/top_level.txt
browserstack.egg-info/zip-safe