Metadata-Version: 1.0
Name: browserstack
Version: 0.1
Summary: Unofficial Python Library for Browserstack
Home-page: https://github.com/tr4n2uil/python-browserstack
Author: Vibhaj Rajan
Author-email: vibhaj8@gmail.com
License: MIT
Keywords: python browserstack
Platform: UNKNOWN
